{
  "RTA in Japan Winter 2025": {"tw": null, "jp": null, "en": null},


  "星のカービィ Wii デラックス": {
    "tw": "星之卡比 Wii 豪華版",
    "jp": "星のカービィ Wii デラックス",
    "en": "Kirby's Return to Dream Land Deluxe",
    "boxart": "https://static-cdn.jtvnw.net/ttv-boxart/1262582393_IGDB.jpg",
    "leaderboard": "https://www.speedrun.com/krtdldx",
    "bangumi": {
      "Magolor Epilogue All Stages": [
        "魔法洛亞後記，跑完全關卡",
        "活動第一棒擔當！任天堂作品重返 RiJ",
        null
      ]
    }
  },
  "Pizza Tower": {
    "tw": "披薩塔",
    "jp": null,
    "en": "Pizza Tower",
    "boxart": "https://static-cdn.jtvnw.net/ttv-boxart/1774510513_IGDB.jpg",
    "leaderboard": "https://www.speedrun.com/pizza_tower",
    "bangumi": {
      "100%,Peppino": [
        "使用角色「佩皮諾」完成 100% 全收集",
        null,
        null
      ]
    }
  },
  "GS美神 ～除霊師はナイスバディ～": {
    "tw": "GS美神 ～Nice Body 除靈師～",
    "jp": "GS美神 ～除霊師はナイスバディ～",
    "en": "Ghost Sweeper Mikami: Joreishi wa Nice Body",
    "boxart": "https://static-cdn.jtvnw.net/ttv-boxart/30340_IGDB.jpg",
    "leaderboard": "https://www.speedrun.com/nice_body",
    "bangumi": {
      "Any%": [
        "【競速 Race】Any%",
        "漫畫《GS 美神 極樂大作戰！！》改編遊戲<br>性感美腿風格的電視 CM 真的沒問題 (?)",
        null
      ]
    }
  },
  "ゴミ箱 -GOMIBAKO-": {
    "tw": "垃圾桶 -GOMIBAKO-",
    "jp": "ゴミ箱 -GOMIBAKO-",
    "en": "Trash Panic",
    "boxart": "https://static-cdn.jtvnw.net/ttv-boxart/21792_IGDB.jpg",
    "leaderboard": "https://www.speedrun.com/thpn",
    "bangumi": {
      "Hellish Shining Gold Can": [
        "地獄級金色罐罐",
        "PS3 時期的西瓜遊戲！？<br>挑戰最上級難度 x 最高評價",
        null
      ]
    }
  },
  "ポケモンでパネポン": {
    "tw": "寶可夢拼圖挑戰",
    "jp": "ポケモンでパネポン",
    "en": "Pokémon Puzzle Challenge",
    "boxart": "https://static-cdn.jtvnw.net/ttv-boxart/8038_IGDB.jpg",
    "leaderboard": "https://www.speedrun.com/pokemon_puzzle_challenge",
    "bangumi": {
      "VS COM EASY - V-HARD(ばくはつせりあげOFF)": [
        "擊敗全難度 CPU<br>消除期間也能進行堆疊的「爆發堆疊」功能 OFF",
        "以 GB《ヨッシーのパネポン》(耀西的面板方塊) 為基礎製作<br>角色採用寶可夢金銀版，並且改善了操作性，作為掌機版表現相當不錯",
        null
      ]
    }
  },
  "アケアカNEOGEO パズルボブル2": {
    "tw": "ACA NEOGEO 泡泡龍2",
    "jp": "アケアカNEOGEO パズルボブル2",
    "en": "Puzzle Bobble 2 / Bust-A-Move Again",
    "boxart": "https://static-cdn.jtvnw.net/ttv-boxart/1035907636_IGDB.jpg",
    "leaderboard": "https://www.speedrun.com/puzzle_bobble_2_arcade",
    "bangumi": {
      "Puzzle": [
        "【競速 Race】Puzzle",
        null,
        null
      ]
    }
  },
  "月光妖怪": {
    "tw": "月光妖怪",
    "jp": null,
    "en": "Moonlight Ghost",
    "boxart": "https://www.speedrun.com/static/game/3dxkjyv1/cover.png",
    "leaderboard": "https://www.speedrun.com/moonlight_ghost",
    "bangumi": {
      "Any% 4chapter": [
        null,
        "RPG Maker x 逆恐怖遊戲",
        null
      ]
    }
  },
  "東方紅魔郷 〜 the Embodiment of Scarlet Devil.": {
    "tw": "東方紅魔鄉",
    "jp": "東方紅魔郷 〜 the Embodiment of Scarlet Devil.",
    "en": "Touhou Koumakyou ~ the Embodiment of Scarlet Devil",
    "boxart": "https://static-cdn.jtvnw.net/ttv-boxart/19951_IGDB.jpg",
    "leaderboard": "https://www.speedrun.com/eosd",
    "bangumi": {
      "Lunatic スコアアタック": [
        "Lunatic 模式 + 刷分挑戰 Score Attack",
        "ZUN 首次以「上海愛麗絲幻樂團」名義發佈的遊戲作品<br>在華麗彈幕下極限擦彈賺分",
        null
      ]
    }
  },
  "PUNCH-OUT!!": {
    "tw": "擊拳熱鬥！！",
    "jp": null,
    "en": "PUNCH-OUT!! (2009)",
    "boxart": "https://www.speedrun.com/static/game/9d37o96l/cover.png",
    "leaderboard": "https://www.speedrun.com/powii",
    "bangumi": {
      "All Fights（目隠し）": [
        "blindfold 蒙眼挑戰，打倒所有拳手",
        "盲拳打死老師傅...你是說真的看不到！？",
        null
      ]
    }
  },
  "世界樹の迷宮Ⅳ 伝承の巨神": {
    "tw": "世界樹迷宮IV 傳承的巨神",
    "jp": "世界樹の迷宮IV 伝承の巨神",
    "en": "Etrian Odyssey IV: Legends of the Titan",
    "boxart": "https://static-cdn.jtvnw.net/ttv-boxart/33691_IGDB.jpg",
    "leaderboard": "https://www.speedrun.com/eo4",
    "bangumi": {
      "Any%": [
        null,
        "「世界樹に至り、その真実を解明せよ！」<br>「抵達世界樹，揭開真相吧！」",
        null
      ]
    }
  },


  "Aliens: Colonial Marines": {
    "tw": "異形：殖民戰隊",
    "jp": null,
    "en": "Aliens: Colonial Marines",
    "boxart": "https://static-cdn.jtvnw.net/ttv-boxart/19100_IGDB.jpg",
    "leaderboard": "https://www.speedrun.com/acm",
    "bangumi": {
      "Any%": [
        null,
        null,
        null
      ]
    }
  },
  "リトルタウンヒーロー": {
    "tw": "小鎮英雄",
    "jp": "リトルタウンヒーロー",
    "en": "Little Town Hero",
    "boxart": "https://static-cdn.jtvnw.net/ttv-boxart/1876836402_IGDB.jpg",
    "leaderboard": "https://www.speedrun.com/little_town_hero",
    "bangumi": {
      "Any% - Difficulty Hard": [
        null,
        null,
        null
      ]
    }
  },
  "桃太郎電鉄ワールド〜地球は希望でまわってる！〜": {
    "tw": "桃太郎電鐵世界",
    "jp": "桃太郎電鉄ワールド〜地球は希望でまわってる！〜",
    "en": "Momotaro Dentetsu World: Chikyuu ha Kibou de Mawatteru!",
    "boxart": "https://static-cdn.jtvnw.net/ttv-boxart/1972874741_IGDB.jpg",
    "leaderboard": null,
    "bangumi": {
      "Get Momotaro Land(With Save)": [
        null,
        null,
        null
      ]
    }
  },
  "BORDER BREAK(PS4)": {
    "tw": "邊境保衛戰",
    "jp": null,
    "en": "Border Break",
    "boxart": "https://static-cdn.jtvnw.net/ttv-boxart/22813_IGDB.jpg",
    "leaderboard": "https://www.speedrun.com/border_break",
    "bangumi": {
      "MainScenario(episode 1 - episode 16) ALL A(1Hangar)": [
        null,
        null,
        null
      ]
    }
  },
  "精霊機フレイリート": {
    "tw": "精靈機弗烈利特",
    "jp": "精霊機フレイリート",
    "en": "Divine Dynamo Flamefrit",
    "boxart": "https://www.speedrun.com/static/game/9d3wnq91/cover.png",
    "leaderboard": "https://www.speedrun.com/Divine_Dynamo_Flamefrit",
    "bangumi": {
      "Any%": [
        null,
        null,
        null
      ]
    }
  },
  "スターフォックス64": {
    "tw": "星際火狐64",
    "jp": "スターフォックス64",
    "en": "Star Fox 64",
    "boxart": "https://static-cdn.jtvnw.net/ttv-boxart/17586_IGDB.jpg",
    "leaderboard": "https://www.speedrun.com/sf64",
    "bangumi": {
      "Any%": [
        null,
        null,
        null
      ]
    }
  },
  "BLADE CHIMERA - ブレードキメラ": {
    "tw": "幻刃奇美拉",
    "jp": "ブレードキメラ",
    "en": "BLADE CHIMERA",
    "boxart": "https://static-cdn.jtvnw.net/ttv-boxart/1982133350_IGDB.jpg",
    "leaderboard": "https://www.speedrun.com/BLADE_CHIMERA",
    "bangumi": {
      "Any%": [
        null,
        null,
        null
      ]
    }
  },
  "MOMIBOSU": {
    "tw": null,
    "jp": "モミボス",
    "en": "MOMIBOSU",
    "boxart": "https://www.speedrun.com/static/game/9doxeq7d/cover.jpg",
    "leaderboard": "https://www.speedrun.com/MOMIBOSU",
    "bangumi": {
      "All Keys": [
        null,
        null,
        null
      ]
    }
  },
  "Lonely Mountains: Snow Riders": {
    "tw": null,
    "jp": null,
    "en": "Lonely Mountains: Snow Riders",
    "boxart": "https://static-cdn.jtvnw.net/ttv-boxart/2109314477_IGDB.jpg",
    "leaderboard": "https://www.speedrun.com/Lonely_Mountains_Snow_Riders",
    "bangumi": {
      "24 Trails": [
        null,
        null,
        null
      ]
    }
  },
  "マリオカート8": {
    "tw": "瑪利歐賽車8",
    "jp": "マリオカート8",
    "en": "Mario Kart 8",
    "boxart": "https://static-cdn.jtvnw.net/ttv-boxart/369588_IGDB.jpg",
    "leaderboard": "https://www.speedrun.com/mk8",
    "bangumi": {
      "48 Tracks": [
        null,
        null,
        null
      ]
    }
  },
  "首都高バトル": {
    "tw": "首都高賽車",
    "jp": "首都高バトル",
    "en": "Shutokou Battle / Tokyo Xtreme Racer",
    "boxart": "https://static-cdn.jtvnw.net/ttv-boxart/6408_IGDB.jpg",
    "leaderboard": "https://www.speedrun.com/tokyo_xtreme_racer",
    "bangumi": {
      "Beat All the Devas": [
        null,
        null,
        null
      ]
    }
  },
  "モンスターハンターワイルズ": {
    "tw": "魔物獵人荒野",
    "jp": "モンスターハンターワイルズ",
    "en": "Monster Hunter Wilds",
    "boxart": "https://static-cdn.jtvnw.net/ttv-boxart/1286077738_IGDB.jpg",
    "leaderboard": "https://www.speedrun.com/mhwilds",
    "bangumi": {
      "Any%": [
        null,
        null,
        null
      ]
    }
  },
  "オウガバトル64 Person of Lordly Caliber": {
    "tw": "皇家騎士團64",
    "jp": "オウガバトル64 Person of Lordly Caliber",
    "en": "Ogre Battle 64: Person of Lordly Caliber",
    "boxart": "https://static-cdn.jtvnw.net/ttv-boxart/13310_IGDB.jpg",
    "leaderboard": "https://www.speedrun.com/ogre_battle_64_person_of_lordly_caliber",
    "bangumi": {
      "Any%": [
        null,
        null,
        null
      ]
    }
  },
  "シャドウジェネレーションズ": {
    "tw": "夏特 世代",
    "jp": "シャドウジェネレーションズ",
    "en": "Shadow Generations",
    "boxart": "https://static-cdn.jtvnw.net/ttv-boxart/1775804061_IGDB.jpg",
    "leaderboard": "https://www.speedrun.com/shadow_generations",
    "bangumi": {
      "Any%": [
        "Any%",
        "黑暗英雄「夏特」肆意奔馳的完全新作《夏特 世代》",
        null
      ]
    }
  },
  "Super High Ball: Pinball Platformer": {
    "tw": null,
    "jp": null,
    "en": "Super High Ball: Pinball Platformer",
    "boxart": "https://static-cdn.jtvnw.net/ttv-boxart/517418_IGDB.jpg",
    "leaderboard": "https://www.speedrun.com/super_high_ball_pinball_platformer",
    "bangumi": {
      "All Levels": [
        null,
        null,
        null
      ]
    }
  },
  "グレゴリーホラーショー ソウルコレクター": {
    "tw": "葛瑞格利驚悚秀",
    "jp": "グレゴリーホラーショー ソウルコレクター",
    "en": "Gregory Horror Show",
    "boxart": "https://static-cdn.jtvnw.net/ttv-boxart/6366_IGDB.jpg",
    "leaderboard": "https://www.speedrun.com/gregory_horror_show",
    "bangumi": {
      "Any%(Normal)": [
        null,
        null,
        null
      ]
    }
  },
  "マリオゴルフGB": {
    "tw": "瑪利歐高爾夫GB",
    "jp": "マリオゴルフGB",
    "en": "Mario Golf (Game Boy Color)",
    "boxart": "https://static-cdn.jtvnw.net/ttv-boxart/18042_IGDB.jpg",
    "leaderboard": "https://www.speedrun.com/mariogolf",
    "bangumi": {
      "Story Mode - All Courses（Switch版）": [
        "故事模式真結局 (Switch 版)",
        "包含原創角色、養成要素和故事模式的異色作品",
        null
      ]
    }
  },
  "Refind Self: 性格診断ゲーム": {
    "tw": "憶我：一個性格測試遊戲",
    "jp": "Refind Self: 性格診断ゲーム",
    "en": "Refind Self: The Personality Test Game",
    "boxart": "https://static-cdn.jtvnw.net/ttv-boxart/235446742_IGDB.jpg",
    "leaderboard": "https://www.speedrun.com/Refind_Self_The_Personality_Test_Game",
    "bangumi": {
      "All Personalities": [
        "全性格取得",
        "「遊戲能夠展現一個人的個性吧？」<br>...可是這款遊戲全部有 23 種性格啊？",
        null
      ]
    }
  },
  "マリオストーリー": {
    "tw": "紙片瑪利歐",
    "jp": "マリオストーリー",
    "en": "Paper Mario",
    "boxart": "https://static-cdn.jtvnw.net/ttv-boxart/18231_IGDB.jpg",
    "leaderboard": "https://www.speedrun.com/pm64",
    "bangumi": {
      "Any%(NoACE)": [
        null,
        "在如同繪本般的世界中，瑪利歐大顯身手！",
        null
      ]
    }
  },
  "エイリアンVSプレデター": {
    "tw": "異形戰場",
    "jp": "エイリアンVSプレデター",
    "en": "Alien Vs Predator",
    "boxart": "https://www.speedrun.com/static/game/46wjw7dr/cover.jpg",
    "leaderboard": "https://www.speedrun.com/avparcade",
    "bangumi": {
      "Schaefer Any%": [
        null,
        null,
        null
      ]
    }
  },
  "キャッスルヴァニア": {
    "tw": "惡魔城 無罪的嘆息",
    "jp": "キャッスルヴァニア",
    "en": "Castlevania: Lament of Innocence",
    "boxart": "https://static-cdn.jtvnw.net/ttv-boxart/14478_IGDB.jpg",
    "leaderboard": "https://www.speedrun.com/loi",
    "bangumi": {
      "Any% Crazy": [
        null,
        "惡魔城系列首次登上 PS2<br>新要素 「效果寶珠系統」打造出多樣的攻擊方式",
        null
      ]
    }
  },
  "小鳩ヶ丘高校女子ぐろ〜部 Gleam of Force": {
    "tw": "小鳩鳩丘高校女子拳鬥部",
    "jp": "小鳩ヶ丘高校女子ぐろ〜部 Gleam of Force",
    "en": "Glove on Fight 2: Gleam of Force",
    "boxart": "https://static-cdn.jtvnw.net/ttv-boxart/495119_IGDB.jpg",
    "leaderboard": "https://www.speedrun.com/glove_on_fight_2__gleam_of_force",
    "bangumi": {
      "STORY HELL%": [
        null,
        null,
        null
      ]
    }
  },
  "Sclash": {
    "tw": null,
    "jp": "スクラシュ",
    "en": "Sclash",
    "boxart": "https://static-cdn.jtvnw.net/ttv-boxart/1166390225_IGDB.jpg",
    "leaderboard": "https://www.speedrun.com/Sclash",
    "bangumi": {
      "Classique": [
        null,
        null,
        null
      ]
    }
  },
  "Vectronom": {
    "tw": null,
    "jp": null,
    "en": "Vectronom",
    "boxart": "https://static-cdn.jtvnw.net/ttv-boxart/512812_IGDB.jpg",
    "leaderboard": "https://www.speedrun.com/vectronom",
    "bangumi": {
      "All Pickups": [
        null,
        null,
        null
      ]
    }
  },
  "A Dance of Fire and Ice": {
    "tw": "冰與火之舞",
    "jp": null,
    "en": "A Dance of Fire and Ice",
    "boxart": "https://static-cdn.jtvnw.net/ttv-boxart/511183_IGDB.jpg",
    "leaderboard": "https://www.speedrun.com/adofai",
    "bangumi": {
      "A100% Pure Perfect": [
        null,
        null,
        null
      ]
    }
  },
  "星のカービィ ウルトラスーパーデラックス": {
    "tw": "星之卡比 超究極豪華版",
    "jp": "星のカービィ ウルトラスーパーデラックス",
    "en": "Kirby Super Star Ultra",
    "boxart": "https://static-cdn.jtvnw.net/ttv-boxart/1146782253_IGDB.jpg",
    "leaderboard": "https://www.speedrun.com/kssu",
    "bangumi": {
      "Beat RotK": [
        "【競速 Race】Beat RotK",
        null,
        null
      ]
    }
  },
  "星のカービィ2": {
    "tw": "星之卡比2",
    "jp": "星のカービィ2",
    "en": "Kirby's Dream Land 2",
    "boxart": "https://static-cdn.jtvnw.net/ttv-boxart/4089_IGDB.jpg",
    "leaderboard": "https://www.speedrun.com/kdl2",
    "bangumi": {
      "Best Ending": [
        null,
        null,
        null
      ]
    }
  },
  "ゼルダ": {
    "tw": "薩爾達",
    "jp": "ゼルダ",
    "en": "Zelda (Game & Watch)",
    "boxart": "https://i.ytimg.com/vi/k7EgqUZ8TBY/maxresdefault.jpg",
    "leaderboard": "https://www.speedrun.com/zelda_game_and_watch",
    "bangumi": {
      "Any%": [
        null,
        "NDS 的靈感來源<br>1980 年任天堂推出的攜帶型遊戲機",
        null
      ]
    }
  },
  "ゼルダの伝説 時のオカリナ": {
    "tw": "薩爾達傳說 時之笛",
    "jp": "ゼルダの伝説 時のオカリナ",
    "en": "The Legend of Zelda: Ocarina of Time",
    "boxart": "https://static-cdn.jtvnw.net/ttv-boxart/11557_IGDB.jpg",
    "leaderboard": "https://www.speedrun.com/oot",
    "bangumi": {
      "MST": [
        null,
        null,
        null
      ]
    }
  },
  "サラダの国のトマト姫": {
    "tw": "沙拉王國的番茄公主",
    "jp": "サラダの国のトマト姫",
    "en": "Princess Tomato in the Salad Kingdom",
    "boxart": "https://static-cdn.jtvnw.net/ttv-boxart/4164_IGDB.jpg",
    "leaderboard": "https://www.speedrun.com/princess_tomato_in_the_salad_kingdom",
    "bangumi": {
      "Beat The Game": [
        null,
        null,
        null
      ]
    }
  },


  "トマトアドベンチャー": {
    "tw": "蕃茄冒險記",
    "jp": "トマトアドベンチャー",
    "en": "Tomato Adventure",
    "boxart": "https://static-cdn.jtvnw.net/ttv-boxart/19331_IGDB.jpg",
    "leaderboard": "https://www.speedrun.com/tomato_adventure",
    "bangumi": {
      "Any%": [
        null,
        null,
        null
      ]
    }
  },
  "不思議のダンジョン 風来のシレン6 とぐろ島探検録": {
    "tw": "千變的迷宮 風來的希煉6 蛇蜷島探險譚",
    "jp": "不思議のダンジョン 風来のシレン6 とぐろ島探検録",
    "en": "Shiren the Wanderer: The Mystery Dungeon of Serpentcoil Island",
    "boxart": "https://static-cdn.jtvnw.net/ttv-boxart/422208436_IGDB.jpg",
    "leaderboard": "https://www.speedrun.com/shiren6",
    "bangumi": {
      "超・神髄TA": [
        "【競速 Race】超・神髄TA",
        null,
        null
      ]
    }
  },
  "ドラゴンクエストキャラクターズ トルネコの大冒険2 不思議のダンジョン": {
    "tw": "特魯內克大冒險2 不思議的迷宮",
    "jp": "ドラゴンクエストキャラクターズ トルネコの大冒険2 不思議のダンジョン",
    "en": "Torneko: The Last Hope",
    "boxart": "https://www.speedrun.com/static/game/4d73x317/cover.jpg",
    "leaderboard": "https://www.speedrun.com/tornekolasthope",
    "bangumi": {
      "Any%": [
        "【競速 Race】Any%",
        null,
        null
      ]
    }
  },
  "スペルトナエル": {
    "tw": "咒語詠唱",
    "jp": "スペルトナエル",
    "en": "Spell Tonaeru",
    "boxart": "https://static-cdn.jtvnw.net/ttv-boxart/438177464_IGDB.jpg",
    "leaderboard": "https://www.speedrun.com/SpellTonaeru",
    "bangumi": {
      "Perfect All Endings": [
        null,
        null,
        null
      ]
    }
  },
  "カエルの為に鐘は鳴る": {
    "tw": "鐘為蛙鳴 / 鐘為青蛙而響",
    "jp": "カエルの為に鐘は鳴る",
    "en": "Kaeru no Tame ni Kane wa Naru",
    "boxart": "https://static-cdn.jtvnw.net/ttv-boxart/9361_IGDB.jpg",
    "leaderboard": "https://www.speedrun.com/kaeru",
    "bangumi": {
      "Any%": [
        null,
        "「表面看起來像是普通的 RPG」",
        null
      ]
    }
  },
  "ピクミン4": {
    "tw": "皮克敏4",
    "jp": "ピクミン4",
    "en": "Pikmin 4",
    "boxart": "https://static-cdn.jtvnw.net/ttv-boxart/494998_IGDB.jpg",
    "leaderboard": "https://www.speedrun.com/pikmin4",
    "bangumi": {
      "Rescue Olimar": [
        "【競速 Race】Rescue Olimar",
        null,
        null
      ]
    }
  },
  "Crab Champions": {
    "tw": "螃蟹冠軍",
    "jp": null,
    "en": "Crab Champions",
    "boxart": "https://static-cdn.jtvnw.net/ttv-boxart/1754564141_IGDB.jpg",
    "leaderboard": "https://www.speedrun.com/crab_champions",
    "bangumi": {
      "Normal Any% No Key Totem(v2194+)": [
        null,
        null,
        null
      ]
    }
  },
  "スーパーマリオワールド": {
    "tw": "超級瑪利歐世界",
    "jp": "スーパーマリオワールド",
    "en": "Super Mario World",
    "boxart": "https://static-cdn.jtvnw.net/ttv-boxart/1229_IGDB.jpg",
    "leaderboard": "https://www.speedrun.com/smw",
    "bangumi": {
      "Small Only": [
        null,
        null,
        null
      ]
    }
  },
  "スーパーマリオメーカー 2": {
    "tw": "超級瑪利歐創作家 2",
    "jp": "スーパーマリオメーカー 2",
    "en": "Super Mario Maker 2",
    "boxart": "https://static-cdn.jtvnw.net/ttv-boxart/511399_IGDB.jpg",
    "leaderboard": "https://www.speedrun.com/smm2",
    "bangumi": {
      "Endless Mode - All Difficulties": [
        null,
        null,
        null
      ]
    }
  },
  "スーパーマリオギャラクシー": {
    "tw": "超級瑪利歐銀河",
    "jp": "スーパーマリオギャラクシー",
    "en": "Super Mario Galaxy",
    "boxart": "https://static-cdn.jtvnw.net/ttv-boxart/14766_IGDB.jpg",
    "leaderboard": "https://www.speedrun.com/smg1",
    "bangumi": {
      "Any% Luigi 1P": [
        null,
        null,
        null
      ]
    }
  },
  "フィズとにじいろの星": {
    "tw": "菲茲與彩虹星",
    "jp": "フィズとにじいろの星",
    "en": "Fiz and the Rainbow Planet",
    "boxart": "https://static-cdn.jtvnw.net/ttv-boxart/534683438_IGDB.jpg",
    "leaderboard": "https://www.speedrun.com/Fiz_and_the_Rainbow_Planet",
    "bangumi": {
      "Any%": [
        null,
        null,
        null
      ]
    }
  },
  "SONOKUNI": {
    "tw": null,
    "jp": null,
    "en": "SONOKUNI",
    "boxart": "https://static-cdn.jtvnw.net/ttv-boxart/429213682_IGDB.jpg",
    "leaderboard": "https://www.speedrun.com/SONOKUNI",
    "bangumi": {
      "Speedrun Mode Hard": [
        null,
        null,
        null
      ]
    }
  },
  "朧村正 - 元禄怪奇譚": {
    "tw": "朧村正 元禄怪奇譚",
    "jp": null,
    "en": "Muramasa Rebirth: Genroku Legends",
    "boxart": "https://static-cdn.jtvnw.net/ttv-boxart/21767_IGDB.jpg",
    "leaderboard": "https://www.speedrun.com/muramasa",
    "bangumi": {
      "Okoi Any%": [
        "化貓篇 Any%",
        null,
        null
      ]
    }
  },
  "Death's Door": {
    "tw": "死亡之門",
    "jp": null,
    "en": "Death's Door",
    "boxart": "https://static-cdn.jtvnw.net/ttv-boxart/1566403385_IGDB.jpg",
    "leaderboard": "https://www.speedrun.com/deaths_door",
    "bangumi": {
      "Unrestricted Latest Patch Any Weapon": [
        null,
        null,
        null
      ]
    }
  },


  "Smash T.V.": {
    "tw": null,
    "jp": null,
    "en": "Smash T.V.",
    "boxart": "https://static-cdn.jtvnw.net/ttv-boxart/14849_IGDB.jpg",
    "leaderboard": null,
    "bangumi": {
      "ノーコンティニューRTA": [
        null,
        null,
        null
      ]
    }
  },
  "近畿霊務局 - Kinki Spiritual Affairs Bureau": {
    "tw": "近畿靈務局",
    "jp": null,
    "en": "Kinki Spiritual Affairs Bureau",
    "boxart": "https://static-cdn.jtvnw.net/ttv-boxart/936475509_IGDB.jpg",
    "leaderboard": "https://www.speedrun.com/Kinki_Spiritual_Affairs_Bureau",
    "bangumi": {
      "［任意の難易度］Any%": [
        null,
        null,
        null
      ]
    }
  },
  "サモンナイト3(PS2版)": {
    "tw": "召喚夜響曲3",
    "jp": "サモンナイト3",
    "en": "Summon Night 3",
    "boxart": "https://static-cdn.jtvnw.net/ttv-boxart/2792_IGDB.jpg",
    "leaderboard": null,
    "bangumi": {
      "NG 通常ルート Any%": [
        null,
        null,
        null
      ]
    }
  },
  "ゼルダの伝説 神々のトライフォース2": {
    "tw": "薩爾達傳說 眾神的三角神力2",
    "jp": "ゼルダの伝説 神々のトライフォース2",
    "en": "The Legend of Zelda: A Link Between Worlds",
    "boxart": "https://static-cdn.jtvnw.net/ttv-boxart/369088_IGDB.jpg",
    "leaderboard": "https://www.speedrun.com/albw",
    "bangumi": {
      "Any%": [
        null,
        null,
        null
      ]
    }
  },
  "ゼルダの伝説 風のタクト": {
    "tw": "薩爾達傳說 風之律動",
    "jp": "ゼルダの伝説 風のタクト",
    "en": "The Legend of Zelda: The Wind Waker",
    "boxart": "https://static-cdn.jtvnw.net/ttv-boxart/16967_IGDB.jpg",
    "leaderboard": "https://www.speedrun.com/tww",
    "bangumi": {
      "All Dungeons": [
        null,
        null,
        null
      ]
    }
  },
  "ゼルダの伝説 知恵のかりもの": {
    "tw": "薩爾達傳說 智慧的再現",
    "jp": "ゼルダの伝説 知恵のかりもの",
    "en": "The Legend of Zelda: Echoes of Wisdom",
    "boxart": "https://static-cdn.jtvnw.net/ttv-boxart/1290989747_IGDB.jpg",
    "leaderboard": "https://www.speedrun.com/eow",
    "bangumi": {
      "Glitchless": [
        null,
        null,
        null
      ]
    }
  },
  "エスパ冒険隊 魔王の砦": {
    "tw": "超能力冒險隊 魔王的城寨",
    "jp": "エスパ冒険隊 魔王の砦",
    "en": "Esper Boukentai",
    "boxart": "https://www.speedrun.com/static/game/pdvon91w/cover.png",
    "leaderboard": "https://www.speedrun.com/esper_boukentai",
    "bangumi": {
      "Any%": [
        null,
        null,
        null
      ]
    }
  },
  "ロマンシング サガ2 リベンジオブザセブン": {
    "tw": "復活邪神2 七英雄的復仇",
    "jp": "ロマンシング サガ2 リベンジオブザセブン",
    "en": "Romancing SaGa 2: Revenge of the Seven",
    "boxart": "https://static-cdn.jtvnw.net/ttv-boxart/1990731722_IGDB.jpg",
    "leaderboard": "https://www.speedrun.com/Romancing_Saga_2_Revenge_of_the_Seven",
    "bangumi": {
      "CASUAL Ver1.1.0": [
        null,
        null,
        null
      ]
    }
  },
  "イレギュラーハンターX": {
    "tw": "反亂獵人X",
    "jp": "イレギュラーハンターX",
    "en": "Irregular Hunter X / Mega Man Maverick Hunter X",
    "boxart": "https://static-cdn.jtvnw.net/ttv-boxart/347261884_IGDB.jpg",
    "leaderboard": "https://www.speedrun.com/megaman_maverick_hunter_x",
    "bangumi": {
      "VAVA Hard 100%": [
        null,
        null,
        null
      ]
    }
  },
  "ロックマンX3": {
    "tw": "洛克人X3",
    "jp": "ロックマンX3",
    "en": "Rockman X3 / Mega Man X3",
    "boxart": "https://static-cdn.jtvnw.net/ttv-boxart/15538_IGDB.jpg",
    "leaderboard": "https://www.speedrun.com/mmx3",
    "bangumi": {
      "Any%": [
        null,
        null,
        null
      ]
    }
  },
  "ドンキーコング リターンズ HD": {
    "tw": "咚奇剛歸來HD",
    "jp": "ドンキーコング リターンズ HD",
    "en": "Donkey Kong Country Returns HD",
    "boxart": "https://static-cdn.jtvnw.net/ttv-boxart/478131056_IGDB.jpg",
    "leaderboard": "https://www.speedrun.com/dkcrhd",
    "bangumi": {
      "Any% Modern Mode": [
        "【競速 Race】Any% Modern Mode",
        null,
        null
      ]
    }
  },
  "罪と罰 〜地球の継承者〜": {
    "tw": "罪與罰 ～地球的繼承者～",
    "jp": "罪と罰 〜地球の継承者〜",
    "en": "Sin and Punishment",
    "boxart": "https://static-cdn.jtvnw.net/ttv-boxart/6772_IGDB.jpg",
    "leaderboard": "https://www.speedrun.com/sandp",
    "bangumi": {
      "Any% Hard": [
        null,
        null,
        null
      ]
    }
  },
  "Final Fantasy 1 Pixel Remaster": {
    "tw": "Final Fantasy 1 像素複刻版",
    "jp": null,
    "en": "Final Fantasy 1 Pixel Remaster",
    "boxart": "https://www.speedrun.com/static/game/ldeyrj13/cover.png",
    "leaderboard": "https://www.speedrun.com/ff1",
    "bangumi": {
      "Any% (No QS Manip)": [
        null,
        null,
        null
      ]
    }
  },
  "ドラゴンクエストモンスターズ テリーのワンダーランド3D": {
    "tw": "勇者鬥惡龍 怪獸仙境 泰瑞的仙境3D",
    "jp": "ドラゴンクエストモンスターズ テリーのワンダーランド3D",
    "en": "Dragon Quest Monsters: Terry no Wonderland 3D",
    "boxart": "https://static-cdn.jtvnw.net/ttv-boxart/1105212777_IGDB.jpg",
    "leaderboard": null,
    "bangumi": {
      "Any%": [
        null,
        null,
        null
      ]
    }
  },


  "ポケットモンスター スカーレット・バイオレット": {
    "tw": "寶可夢 朱／紫",
    "jp": "ポケットモンスター スカーレット・バイオレット",
    "en": "Pokémon Scarlet and Violet",
    "boxart": "https://static-cdn.jtvnw.net/ttv-boxart/670867987.jpg",
    "leaderboard": "https://www.speedrun.com/pkmnscarletviolet",
    "bangumi": {
      "Any% Glitchless": [
        "【競速 Race】Any% Glitchless",
        null,
        null
      ]
    }
  },
  "リトルウィッチノベタ": {
    "tw": "小魔女諾貝塔",
    "jp": "リトルウィッチノベタ",
    "en": "Little Witch Nobeta",
    "boxart": "https://static-cdn.jtvnw.net/ttv-boxart/515621_IGDB.jpg",
    "leaderboard": "https://www.speedrun.com/little_witch_nobeta",
    "bangumi": {
      "NewGame, Unrestricted, STANDARD, \u0022All-Items\u0022": [
        "全物品收集 (一週目 / BUG 無限制 / Standard 難度)",
        null,
        null
      ]
    }
  },
  "Ambidextro": {
    "tw": null,
    "jp": null,
    "en": "Ambidextro",
    "boxart": "https://static-cdn.jtvnw.net/ttv-boxart/1427281643_IGDB.jpg",
    "leaderboard": "https://www.speedrun.com/Ambidextro",
    "bangumi": {
      "Any% No Major Glitches": [
        null,
        null,
        null
      ]
    }
  },
  "そろそろ寿司を食べないと死ぬぜ！ユニバース": {
    "tw": "壽司靈魂宇宙",
    "jp": "そろそろ寿司を食べないと死ぬぜ！ユニバース",
    "en": "Sushi Soul Universe",
    "boxart": "https://static-cdn.jtvnw.net/ttv-boxart/19293055_IGDB.jpg",
    "leaderboard": "https://www.speedrun.com/SUSHI_SOUL_UNIVERSE",
    "bangumi": {
      "Any%": [
        null,
        null,
        null
      ]
    }
  },
  "カドゥケウスZ 2つの超執刀": {
    "tw": "神使之杖Z 雙超執刀",
    "jp": "カドゥケウスZ 2つの超執刀",
    "en": "Trauma Center: Second Opinion",
    "boxart": "https://static-cdn.jtvnw.net/ttv-boxart/540860743_IGDB.jpg",
    "leaderboard": "https://www.speedrun.com/tcso",
    "bangumi": {
      "Any% Normal": [
        null,
        null,
        null
      ]
    }
  },
  "ゼノブレイド3 新たなる未来": {
    "tw": "異度神劍3 嶄新的未來",
    "jp": "ゼノブレイド3 新たなる未来",
    "en": "Xenoblade Chronicles 3: Future Redeemed",
    "boxart": "https://www.speedrun.com/static/game/v1pxn346/cover.jpg",
    "leaderboard": "https://www.speedrun.com/xcfr",
    "bangumi": {
      "Any% - Easy": [
        null,
        null,
        null
      ]
    }
  },
  "ディディーコングレーシング": {
    "tw": "迪迪剛賽車",
    "jp": "ディディーコングレーシング",
    "en": "Diddy Kong Racing",
    "boxart": "https://static-cdn.jtvnw.net/ttv-boxart/14660_IGDB.jpg",
    "leaderboard": "https://www.speedrun.com/dkr",
    "bangumi": {
      "100%": [
        "【競速 Race】100%",
        null,
        null
      ]
    }
  },
  "魂斗羅 オペレーション ガルガ": {
    "tw": "魂斗羅：加盧加行動",
    "jp": "ディディーコングレーシング",
    "en": "Contra: Operation Galuga",
    "boxart": "https://static-cdn.jtvnw.net/ttv-boxart/537410450_IGDB.jpg",
    "leaderboard": "https://www.speedrun.com/Contra_Operation_Galuga",
    "bangumi": {
      "Any% Arcade/Bill Rizer/Normal/Health Meter/Perks": [
        null,
        null,
        null
      ]
    }
  },
  "バベルの塔": {
    "tw": "巴比倫塔",
    "jp": "バベルの塔",
    "en": "Tower of Babel",
    "boxart": "https://www.speedrun.com/static/game/j1n82gl1/cover.jpg",
    "leaderboard": "https://www.speedrun.com/the_tower_of_babel",
    "bangumi": {
      "Pro (Original Version)": [
        null,
        null,
        null
      ]
    }
  },
  "Good Job!": {
    "tw": null,
    "jp": null,
    "en": "Good Job!",
    "boxart": "https://static-cdn.jtvnw.net/ttv-boxart/516848_IGDB.jpg",
    "leaderboard": "https://www.speedrun.com/good_job",
    "bangumi": {
      "New Game Any% Damageless": [
        null,
        null,
        null
      ]
    }
  },
  "A Tiny Sticker Tale": {
    "tw": "小貼紙故事",
    "jp": null,
    "en": "A Tiny Sticker Tale",
    "boxart": "https://static-cdn.jtvnw.net/ttv-boxart/910625605_IGDB.jpg",
    "leaderboard": "https://www.speedrun.com/a_tiny_Sticker_Tale",
    "bangumi": {
      "All Stickers": [
        null,
        null,
        null
      ]
    }
  },
  "遊☆戯☆王デュエルモンスターズ4 最強決闘者戦記": {
    "tw": "遊戲王 怪獸之決鬥4 最強決鬥者戰記",
    "jp": "遊☆戯☆王デュエルモンスターズ4 最強決闘者戦記",
    "en": "Yu-Gi-Oh! Duel Monsters 4: Battle of Great Duelist",
    "boxart": "https://www.speedrun.com/static/game/3dxk09g1/cover.jpg",
    "leaderboard": "https://www.speedrun.com/yugiohdm4",
    "bangumi": {
      "Any%": [
        "【競速 Race】Any%",
        null,
        null
      ]
    }
  },
  "ペルソナ4 ザ・ゴールデン": {
    "tw": "女神異聞錄4 黃金版",
    "jp": "ペルソナ4 ザ・ゴールデン",
    "en": "Persona 4 Golden",
    "boxart": "https://static-cdn.jtvnw.net/ttv-boxart/32542_IGDB.jpg",
    "leaderboard": "https://www.speedrun.com/p4g",
    "bangumi": {
      "Hard Golden Ending NMG": [
        null,
        null,
        null
      ]
    }
  },


  "Bat to the Heavens": {
    "tw": null,
    "jp": null,
    "en": "Bat to the Heavens",
    "boxart": "https://static-cdn.jtvnw.net/ttv-boxart/1233823310_IGDB.jpg",
    "leaderboard": "https://www.speedrun.com/Bat_to_the_Heavens",
    "bangumi": {
      "54 Lantern": [
        null,
        null,
        null
      ]
    }
  },
  "ヨッシーのクッキー": {
    "tw": "耀西的餅乾",
    "jp": "ヨッシーのクッキー",
    "en": "Yoshi's Cookie",
    "boxart": "https://www.speedrun.com/static/game/o6g2m812/cover.png",
    "leaderboard": "https://www.speedrun.com/yoshis_cookie_snes",
    "bangumi": {
      "VS Mode": [
        null,
        null,
        null
      ]
    }
  },
  "スーパーマリオパーティ ジャンボリー": {
    "tw": "超級瑪利歐派對 空前盛會",
    "jp": "スーパーマリオパーティ ジャンボリー",
    "en": "Super Mario Party Jamboree",
    "boxart": "https://static-cdn.jtvnw.net/ttv-boxart/1471610418_IGDB.jpg",
    "leaderboard": "https://www.speedrun.com/supermariopartyjamboree",
    "bangumi": {
      "Party-Planner Trek Any%": [
        "【競速 Race】Party-Planner Trek Any%",
        null,
        null
      ]
    }
  },
  "スプラトゥーン3 サイド・オーダー": {
    "tw": "斯普拉遁3：秩序篇",
    "jp": "スプラトゥーン3 サイド・オーダー",
    "en": "Splatoon 3: Side Order",
    "boxart": "https://www.speedrun.com/static/game/k6qp2pmd/cover.png",
    "leaderboard": "https://www.speedrun.com/SideOrder",
    "bangumi": {
      "Any%": [
        null,
        null,
        null
      ]
    }
  },
  "Pump It Up Phoenix": {
    "tw": null,
    "jp": null,
    "en": "Pump It Up Phoenix",
    "boxart": "https://static-cdn.jtvnw.net/ttv-boxart/1078451966_IGDB.jpg",
    "leaderboard": null,
    "bangumi": {
      "Showcase": [
        "音樂節奏遊戲表演",
        null,
        null
      ]
    }
  },
  "ENDER MAGNOLIA: Bloom in the Mist": {
    "tw": "終結者瑪格諾莉亞",
    "jp": null,
    "en": "ENDER MAGNOLIA: Bloom in the Mist",
    "boxart": "https://static-cdn.jtvnw.net/ttv-boxart/838184267_IGDB.jpg",
    "leaderboard": "https://www.speedrun.com/endermagnolia",
    "bangumi": {
      "Any% Ending A - Normal": [
        null,
        null,
        null
      ]
    }
  },
  "イースⅡクロニクルズ": {
    "tw": "伊蘇II 編年史",
    "jp": "イースII クロニクルズ",
    "en": "Ys II Chronicles",
    "boxart": "https://www.speedrun.com/static/game/nd2nmrd0/cover.png",
    "leaderboard": "https://www.speedrun.com/ysiic",
    "bangumi": {
      "Easy Any% (No Time Attack glitch)": [
        null,
        null,
        null
      ]
    }
  },
  "スーパーメトロイド": {
    "tw": "超級銀河戰士",
    "jp": "スーパーメトロイド",
    "en": "Super Metroid",
    "boxart": "https://static-cdn.jtvnw.net/ttv-boxart/7595_IGDB.jpg",
    "leaderboard": "https://www.speedrun.com/supermetroid",
    "bangumi": {
      "Reverse Boss Order": [
        "逆順序擊敗頭目",
        null,
        null
      ]
    }
  },


  "【バックアップ】Untitled Goose Game 〜いたずらガチョウがやって来た！〜": {
    "tw": "無名鵝愛搗蛋",
    "jp": "Untitled Goose Game 〜いたずらガチョウがやって来た！〜",
    "en": "Untitled Goose Game",
    "boxart": "https://static-cdn.jtvnw.net/ttv-boxart/499537_IGDB.jpg",
    "leaderboard": "https://www.speedrun.com/goose",
    "bangumi": {
      "100%": [
        "【備選節目 Backup】100%",
        "HOOK～！",
        null
      ]
    }
  },


  "See You Next Time": {"tw": null, "jp": null, "en": null }
}